README.rst
setup.py
sqlacfg/__init__.py
sqlacfg/format.py
sqlacfg.egg-info/PKG-INFO
sqlacfg.egg-info/SOURCES.txt
sqlacfg.egg-info/dependency_links.txt
sqlacfg.egg-info/requires.txt
sqlacfg.egg-info/top_level.txt