Metadata-Version: 1.1
Name: sqlacfg
Version: 0.3
Summary: Stores configurations in a database instead of a file
Home-page: http://github.com/mbr/sqlacfg
Author: Marc Brinkmann
Author-email: git@marcbrinkmann.de
License: MIT
Platform: UNKNOWN
Classifier: Programming Language :: Python :: 2
Classifier: Programming Language :: Python :: 3
